__version__.py
nrel_utility.py
nrel_utility_errors.py
setup.py
pynrelutility.egg-info/PKG-INFO
pynrelutility.egg-info/SOURCES.txt
pynrelutility.egg-info/dependency_links.txt
pynrelutility.egg-info/requires.txt
pynrelutility.egg-info/top_level.txt