Metadata-Version: 1.1
Name: pynrelutility
Version: 0.1.1
Summary: Python interface for NREL's Utility API API. The API is providing                 utility names and rates for a given location
Home-page: https://github.com/hanneshapke/pynrelutility
Author: Hannes Hapke
Author-email: hannes@renooble.com
License: MIT
Download-URL: https://github.com/hanneshapke/pynrelutility/archive/master.zip
Keywords: nrel utility energy electricity rates api json US
Platform: UNKNOWN
Classifier: Development Status :: 3 - Alpha
Classifier: Intended Audience :: Science/Research
Classifier: Natural Language :: English
Classifier: Operating System :: OS Independent
Classifier: Programming Language :: Python :: 2
Classifier: License :: OSI Approved :: BSD License
Classifier: Topic :: Internet
Classifier: Topic :: Internet :: WWW/HTTP
Classifier: Topic :: Scientific/Engineering
Requires: requests
Provides: nrel_utility
